Workbook

Sheet README
A1: Mini Network Planning Workbench - Bengaluru (BLR) hub
A3: What this is | B3: A learning model of a fictional hub-and-spoke airline: 1 hub (BLR) + 6 spokes. It shows how a planner connects schedule, demand, fares and cost to decide: add, hold, watch or cut.
A4: IMPORTANT | B4: All data is synthetic/illustrative. Distances are rounded approximate great-circle values; fares, demand, costs, speeds and turn times are my own assumptions, NOT Sabre or any airline's data. Verify before quoting any number externally.
A5: Colour legend | B5: Blue text on yellow = input you can change. Black = formula. Green = link to another sheet. Do not overwrite black cells.
A6: Tab: Inputs | B6: Scenario levers (demand, fare, cost change), connection rules (MCT, max connect) and the fleet table (seats, speed, cost per block hour, turnaround).
A7: Tab: Markets | B7: One row per spoke: distance, baseline daily demand per direction, average fare, aircraft type, and a frequency adjustment (+/-) for what-if.
A8: Tab: Schedule | B8: One row per aircraft rotation (BLR -> spoke -> BLR). Edit the BLR departure time and spoke; arrival, turnaround and return times are computed. Connection counts show whether the hub banks work.
A9: Tab: Route_PnL | B9: Per-route daily economics: capacity, passengers, spill, load factor, revenue, cost, profit, ASK/RPK, RASK, CASK, yield, breakeven load factor, a recommendation and the profit change from adding one more daily flight. Spill alone never triggers ADD: the extra flight must also be profitable.
A10: How a number flows | B10: Schedule (rotations per spoke) -> frequency -> capacity (seats x flights) -> passengers = MIN(capacity, demand) -> revenue; block time (distance/speed + allowance) -> cost per flight -> profit.
A11: Practice 1 | B11: Set Markets!G for MAA to +3 and F to ATR72. What happens to profit and spill? Why does a smaller aircraft help on a short route?
A12: Practice 2 | B12: Set Inputs!B6 (cost change) to +10%. Which routes flip from HOLD to WATCH or REVIEW? Explain breakeven load factor.
A13: Practice 3 | B13: In Schedule, R19 (BOM) arrives about 10:21, nine minutes after the 10:30 bank leaves. Change its BLR departure to 05:30 and watch the connection counts and flag. Explain MCT and why 'a few minutes late' kills a connection.
A14: Practice 4 | B14: Raise demand 15% in Inputs!B4. Which routes spill, and does adding a flight pay (column X)? What else could you do: bigger aircraft, higher fare?
A15: Limits (be honest in interviews) | B15: No recapture of spilled passengers, no network (O&D) revenue from connecting passengers, no fare classes, no slots, single-day view, two aircraft types only. Real planning tools model all of this.

Sheet Inputs
A1: Inputs and scenario levers
A3: Scenario levers and rules
A4: Demand change vs base | B4: 0 | C4: Scenario lever. 0.1 = +10% demand on every route.
A5: Fare change vs base | B5: 0 | C5: Scenario lever. Applies to all average fares.
A6: Cost change (fuel, charges) | B6: 0 | C6: Scenario lever. Applies to all flight costs.
A7: Minimum connect time, MCT (minutes) | B7: 45 | C7: Assumption: shortest legal/realistic transfer time at the hub. Real MCTs vary by airport, terminal and domestic/international.
A8: Maximum useful connect time (minutes) | B8: 180 | C8: Assumption: connections longer than this are not treated as useful.
A9: Spill threshold to recommend ADD (share of demand) | B9: 0.05 | C9: Assumption: if more than this share of demand is turned away, recommend adding capacity.
A10: Thin-margin threshold (load factor points above breakeven) | B10: 0.03 | C10: Assumption: below this cushion the route is flagged WATCH.
A12: Fleet table (illustrative assumptions - not real airline data)
A13: Aircraft | B13: Seats | C13: Cruise speed (km/h) | D13: Taxi/climb allowance (hrs) | E13: Cost per block hour (INR) | F13: Fixed cost per departure (INR) | G13: Turnaround (min)
A14: A320 | B14: 180 | C14: 800 | D14: 0.5 | E14: 480000 | F14: 150000 | G14: 45
A15: ATR72 | B15: 78 | C15: 500 | D15: 0.4 | E15: 150000 | F15: 50000 | G15: 35
A17: Block time = distance / cruise speed + taxi/climb allowance. Cost per flight = block hours x cost per block hour + fixed cost per departure.

Sheet Markets
A1: Markets (spokes served from BLR)
A2: Blue/yellow cells are inputs. Demand and fare are per direction per day, synthetic. Distances: rounded approximate great-circle, assumption.
A4: Spoke | B4: City | C4: Distance (km) | D4: Base demand (pax/day/direction) | E4: Average fare (INR) | F4: Aircraft | G4: Frequency adjustment (+/- daily flights) | H4: Note
A5: TRV | B5: Thiruvananthapuram | C5: 505 | D5: 640 | E5: 4500 | F5: A320 | G5: 0 | H5: Strong business and leisure market
A6: COK | B6: Kochi | C6: 340 | D6: 300 | E6: 3200 | F6: ATR72 | G6: 0 | H6: Short sector, turboprop fits demand
A7: HYD | B7: Hyderabad | C7: 500 | D7: 640 | E7: 4800 | F7: A320 | G7: 0 | H7: Corporate heavy
A8: MAA | B8: Chennai | C8: 290 | D8: 480 | E8: 3200 | F8: A320 | G8: 0 | H8: Very short sector, jet may be too big/costly
A9: GOI | B9: Goa | C9: 485 | D9: 440 | E9: 4500 | F9: A320 | G9: 0 | H9: Leisure, seasonal
A10: BOM | B10: Mumbai | C10: 845 | D10: 980 | E10: 6200 | F10: A320 | G10: 0 | H10: Trunk route, high demand

Sheet Schedule
A1: Daily rotation schedule (BLR hub)
A2: Share of arrivals (before the last departure) with at least one valid onward connection: | H2: =IF(COUNTIF(H5:H27,"<"&MAX(D5:D27))=0,0,COUNTIFS(I5:I27,">0",H5:H27,"<"&MAX(D5:D27))/COUNTIF(H5:H27,"<"&MAX(D5:D27))) -> 0.83333333
A4: Rotation | B4: Spoke | C4: Aircraft | D4: BLR departure | E4: Block time (hrs, each way) | F4: Arrive spoke | G4: Depart spoke | H4: Arrive BLR | I4: Valid onward connections from this arrival | J4: Valid feeder arrivals into this departure | K4: Check
A5: R01 | B5: TRV | C5: =INDEX(Markets!$F$5:$F$10,MATCH(B5,Markets!$A$5:$A$10,0)) -> A320 | D5: 0.27083333 | E5: =INDEX(Route_PnL!$D$5:$D$10,MATCH(B5,Route_PnL!$A$5:$A$10,0)) -> 1.13125 | F5: =D5+E5/24 -> 0.31796875 | G5: =F5+INDEX(Inputs!$G$14:$G$15,MATCH(C5,Inputs!$A$14:$A$15,0))/1440 -> 0.34921875 | H5: =G5+E5/24 -> 0.39635417 | I5: =SUMPRODUCT(($D$5:$D$27-H5>=Inputs!$B$7/1440)*($D$5:$D$27-H5<=Inputs!$B$8/1440)*($B$5:$B$27<>B5)) -> 5 | J5: =SUMPRODUCT((D5-$H$5:$H$27>=Inputs!$B$7/1440)*(D5-$H$5:$H$27<=Inputs!$B$8/1440)*($B$5:$B$27<>B5)) -> 0 | K5: =IF(AND(I5=0,H5<MAX($D$5:$D$27)),"! arrival misses every onward bank",IF(AND(J5=0,D5>MIN($H$5:$H$27)),"! departure has no feeder","OK")) -> OK
A6: R02 | B6: TRV | C6: =INDEX(Markets!$F$5:$F$10,MATCH(B6,Markets!$A$5:$A$10,0)) -> A320 | D6: 0.4375 | E6: =INDEX(Route_PnL!$D$5:$D$10,MATCH(B6,Route_PnL!$A$5:$A$10,0)) -> 1.13125 | F6: =D6+E6/24 -> 0.48463542 | G6: =F6+INDEX(Inputs!$G$14:$G$15,MATCH(C6,Inputs!$A$14:$A$15,0))/1440 -> 0.51588542 | H6: =G6+E6/24 -> 0.56302083 | I6: =SUMPRODUCT(($D$5:$D$27-H6>=Inputs!$B$7/1440)*($D$5:$D$27-H6<=Inputs!$B$8/1440)*($B$5:$B$27<>B6)) -> 5 | J6: =SUMPRODUCT((D6-$H$5:$H$27>=Inputs!$B$7/1440)*(D6-$H$5:$H$27<=Inputs!$B$8/1440)*($B$5:$B$27<>B6)) -> 4 | K6: =IF(AND(I6=0,H6<MAX($D$5:$D$27)),"! arrival misses every onward bank",IF(AND(J6=0,D6>MIN($H$5:$H$27)),"! departure has no feeder","OK")) -> OK
A7: R03 | B7: TRV | C7: =INDEX(Markets!$F$5:$F$10,MATCH(B7,Markets!$A$5:$A$10,0)) -> A320 | D7: 0.60416667 | E7: =INDEX(Route_PnL!$D$5:$D$10,MATCH(B7,Route_PnL!$A$5:$A$10,0)) -> 1.13125 | F7: =D7+E7/24 -> 0.65130208 | G7: =F7+INDEX(Inputs!$G$14:$G$15,MATCH(C7,Inputs!$A$14:$A$15,0))/1440 -> 0.68255208 | H7: =G7+E7/24 -> 0.7296875 | I7: =SUMPRODUCT(($D$5:$D$27-H7>=Inputs!$B$7/1440)*($D$5:$D$27-H7<=Inputs!$B$8/1440)*($B$5:$B$27<>B7)) -> 4 | J7: =SUMPRODUCT((D7-$H$5:$H$27>=Inputs!$B$7/1440)*(D7-$H$5:$H$27<=Inputs!$B$8/1440)*($B$5:$B$27<>B7)) -> 3 | K7: =IF(AND(I7=0,H7<MAX($D$5:$D$27)),"! arrival misses every onward bank",IF(AND(J7=0,D7>MIN($H$5:$H$27)),"! departure has no feeder","OK")) -> OK
A8: R04 | B8: TRV | C8: =INDEX(Markets!$F$5:$F$10,MATCH(B8,Markets!$A$5:$A$10,0)) -> A320 | D8: 0.77083333 | E8: =INDEX(Route_PnL!$D$5:$D$10,MATCH(B8,Route_PnL!$A$5:$A$10,0)) -> 1.13125 | F8: =D8+E8/24 -> 0.81796875 | G8: =F8+INDEX(Inputs!$G$14:$G$15,MATCH(C8,Inputs!$A$14:$A$15,0))/1440 -> 0.84921875 | H8: =G8+E8/24 -> 0.89635417 | I8: =SUMPRODUCT(($D$5:$D$27-H8>=Inputs!$B$7/1440)*($D$5:$D$27-H8<=Inputs!$B$8/1440)*($B$5:$B$27<>B8)) -> 0 | J8: =SUMPRODUCT((D8-$H$5:$H$27>=Inputs!$B$7/1440)*(D8-$H$5:$H$27<=Inputs!$B$8/1440)*($B$5:$B$27<>B8)) -> 5 | K8: =IF(AND(I8=0,H8<MAX($D$5:$D$27)),"! arrival misses every onward bank",IF(AND(J8=0,D8>MIN($H$5:$H$27)),"! departure has no feeder","OK")) -> OK
A9: R05 | B9: COK | C9: =INDEX(Markets!$F$5:$F$10,MATCH(B9,Markets!$A$5:$A$10,0)) -> ATR72 | D9: 0.27083333 | E9: =INDEX(Route_PnL!$D$5:$D$10,MATCH(B9,Route_PnL!$A$5:$A$10,0)) -> 1.08 | F9: =D9+E9/24 -> 0.31583333 | G9: =F9+INDEX(Inputs!$G$14:$G$15,MATCH(C9,Inputs!$A$14:$A$15,0))/1440 -> 0.34013889 | H9: =G9+E9/24 -> 0.38513889 | I9: =SUMPRODUCT(($D$5:$D$27-H9>=Inputs!$B$7/1440)*($D$5:$D$27-H9<=Inputs!$B$8/1440)*($B$5:$B$27<>B9)) -> 4 | J9: =SUMPRODUCT((D9-$H$5:$H$27>=Inputs!$B$7/1440)*(D9-$H$5:$H$27<=Inputs!$B$8/1440)*($B$5:$B$27<>B9)) -> 0 | K9: =IF(AND(I9=0,H9<MAX($D$5:$D$27)),"! arrival misses every onward bank",IF(AND(J9=0,D9>MIN($H$5:$H$27)),"! departure has no feeder","OK")) -> OK
A10: R06 | B10: COK | C10: =INDEX(Markets!$F$5:$F$10,MATCH(B10,Markets!$A$5:$A$10,0)) -> ATR72 | D10: 0.4375 | E10: =INDEX(Route_PnL!$D$5:$D$10,MATCH(B10,Route_PnL!$A$5:$A$10,0)) -> 1.08 | F10: =D10+E10/24 -> 0.4825 | G10: =F10+INDEX(Inputs!$G$14:$G$15,MATCH(C10,Inputs!$A$14:$A$15,0))/1440 -> 0.50680556 | H10: =G10+E10/24 -> 0.55180556 | I10: =SUMPRODUCT(($D$5:$D$27-H10>=Inputs!$B$7/1440)*($D$5:$D$27-H10<=Inputs!$B$8/1440)*($B$5:$B$27<>B10)) -> 5 | J10: =SUMPRODUCT((D10-$H$5:$H$27>=Inputs!$B$7/1440)*(D10-$H$5:$H$27<=Inputs!$B$8/1440)*($B$5:$B$27<>B10)) -> 4 | K10: =IF(AND(I10=0,H10<MAX($D$5:$D$27)),"! arrival misses every onward bank",IF(AND(J10=0,D10>MIN($H$5:$H$27)),"! departure has no feeder","OK")) -> OK
A11: R07 | B11: COK | C11: =INDEX(Markets!$F$5:$F$10,MATCH(B11,Markets!$A$5:$A$10,0)) -> ATR72 | D11: 0.60416667 | E11: =INDEX(Route_PnL!$D$5:$D$10,MATCH(B11,Route_PnL!$A$5:$A$10,0)) -> 1.08 | F11: =D11+E11/24 -> 0.64916667 | G11: =F11+INDEX(Inputs!$G$14:$G$15,MATCH(C11,Inputs!$A$14:$A$15,0))/1440 -> 0.67347222 | H11: =G11+E11/24 -> 0.71847222 | I11: =SUMPRODUCT(($D$5:$D$27-H11>=Inputs!$B$7/1440)*($D$5:$D$27-H11<=Inputs!$B$8/1440)*($B$5:$B$27<>B11)) -> 4 | J11: =SUMPRODUCT((D11-$H$5:$H$27>=Inputs!$B$7/1440)*(D11-$H$5:$H$27<=Inputs!$B$8/1440)*($B$5:$B$27<>B11)) -> 3 | K11: =IF(AND(I11=0,H11<MAX($D$5:$D$27)),"! arrival misses every onward bank",IF(AND(J11=0,D11>MIN($H$5:$H$27)),"! departure has no feeder","OK")) -> OK
A12: R08 | B12: COK | C12: =INDEX(Markets!$F$5:$F$10,MATCH(B12,Markets!$A$5:$A$10,0)) -> ATR72 | D12: 0.77083333 | E12: =INDEX(Route_PnL!$D$5:$D$10,MATCH(B12,Route_PnL!$A$5:$A$10,0)) -> 1.08 | F12: =D12+E12/24 -> 0.81583333 | G12: =F12+INDEX(Inputs!$G$14:$G$15,MATCH(C12,Inputs!$A$14:$A$15,0))/1440 -> 0.84013889 | H12: =G12+E12/24 -> 0.88513889 | I12: =SUMPRODUCT(($D$5:$D$27-H12>=Inputs!$B$7/1440)*($D$5:$D$27-H12<=Inputs!$B$8/1440)*($B$5:$B$27<>B12)) -> 0 | J12: =SUMPRODUCT((D12-$H$5:$H$27>=Inputs!$B$7/1440)*(D12-$H$5:$H$27<=Inputs!$B$8/1440)*($B$5:$B$27<>B12)) -> 5 | K12: =IF(AND(I12=0,H12<MAX($D$5:$D$27)),"! arrival misses every onward bank",IF(AND(J12=0,D12>MIN($H$5:$H$27)),"! departure has no feeder","OK")) -> OK
A13: R09 | B13: HYD | C13: =INDEX(Markets!$F$5:$F$10,MATCH(B13,Markets!$A$5:$A$10,0)) -> A320 | D13: 0.27083333 | E13: =INDEX(Route_PnL!$D$5:$D$10,MATCH(B13,Route_PnL!$A$5:$A$10,0)) -> 1.125 | F13: =D13+E13/24 -> 0.31770833 | G13: =F13+INDEX(Inputs!$G$14:$G$15,MATCH(C13,Inputs!$A$14:$A$15,0))/1440 -> 0.34895833 | H13: =G13+E13/24 -> 0.39583333 | I13: =SUMPRODUCT(($D$5:$D$27-H13>=Inputs!$B$7/1440)*($D$5:$D$27-H13<=Inputs!$B$8/1440)*($B$5:$B$27<>B13)) -> 5 | J13: =SUMPRODUCT((D13-$H$5:$H$27>=Inputs!$B$7/1440)*(D13-$H$5:$H$27<=Inputs!$B$8/1440)*($B$5:$B$27<>B13)) -> 0 | K13: =IF(AND(I13=0,H13<MAX($D$5:$D$27)),"! arrival misses every onward bank",IF(AND(J13=0,D13>MIN($H$5:$H$27)),"! departure has no feeder","OK")) -> OK
A14: R10 | B14: HYD | C14: =INDEX(Markets!$F$5:$F$10,MATCH(B14,Markets!$A$5:$A$10,0)) -> A320 | D14: 0.4375 | E14: =INDEX(Route_PnL!$D$5:$D$10,MATCH(B14,Route_PnL!$A$5:$A$10,0)) -> 1.125 | F14: =D14+E14/24 -> 0.484375 | G14: =F14+INDEX(Inputs!$G$14:$G$15,MATCH(C14,Inputs!$A$14:$A$15,0))/1440 -> 0.515625 | H14: =G14+E14/24 -> 0.5625 | I14: =SUMPRODUCT(($D$5:$D$27-H14>=Inputs!$B$7/1440)*($D$5:$D$27-H14<=Inputs!$B$8/1440)*($B$5:$B$27<>B14)) -> 5 | J14: =SUMPRODUCT((D14-$H$5:$H$27>=Inputs!$B$7/1440)*(D14-$H$5:$H$27<=Inputs!$B$8/1440)*($B$5:$B$27<>B14)) -> 4 | K14: =IF(AND(I14=0,H14<MAX($D$5:$D$27)),"! arrival misses every onward bank",IF(AND(J14=0,D14>MIN($H$5:$H$27)),"! departure has no feeder","OK")) -> OK
A15: R11 | B15: HYD | C15: =INDEX(Markets!$F$5:$F$10,MATCH(B15,Markets!$A$5:$A$10,0)) -> A320 | D15: 0.60416667 | E15: =INDEX(Route_PnL!$D$5:$D$10,MATCH(B15,Route_PnL!$A$5:$A$10,0)) -> 1.125 | F15: =D15+E15/24 -> 0.65104167 | G15: =F15+INDEX(Inputs!$G$14:$G$15,MATCH(C15,Inputs!$A$14:$A$15,0))/1440 -> 0.68229167 | H15: =G15+E15/24 -> 0.72916667 | I15: =SUMPRODUCT(($D$5:$D$27-H15>=Inputs!$B$7/1440)*($D$5:$D$27-H15<=Inputs!$B$8/1440)*($B$5:$B$27<>B15)) -> 4 | J15: =SUMPRODUCT((D15-$H$5:$H$27>=Inputs!$B$7/1440)*(D15-$H$5:$H$27<=Inputs!$B$8/1440)*($B$5:$B$27<>B15)) -> 3 | K15: =IF(AND(I15=0,H15<MAX($D$5:$D$27)),"! arrival misses every onward bank",IF(AND(J15=0,D15>MIN($H$5:$H$27)),"! departure has no feeder","OK")) -> OK
A16: R12 | B16: HYD | C16: =INDEX(Markets!$F$5:$F$10,MATCH(B16,Markets!$A$5:$A$10,0)) -> A320 | D16: 0.77083333 | E16: =INDEX(Route_PnL!$D$5:$D$10,MATCH(B16,Route_PnL!$A$5:$A$10,0)) -> 1.125 | F16: =D16+E16/24 -> 0.81770833 | G16: =F16+INDEX(Inputs!$G$14:$G$15,MATCH(C16,Inputs!$A$14:$A$15,0))/1440 -> 0.84895833 | H16: =G16+E16/24 -> 0.89583333 | I16: =SUMPRODUCT(($D$5:$D$27-H16>=Inputs!$B$7/1440)*($D$5:$D$27-H16<=Inputs!$B$8/1440)*($B$5:$B$27<>B16)) -> 0 | J16: =SUMPRODUCT((D16-$H$5:$H$27>=Inputs!$B$7/1440)*(D16-$H$5:$H$27<=Inputs!$B$8/1440)*($B$5:$B$27<>B16)) -> 5 | K16: =IF(AND(I16=0,H16<MAX($D$5:$D$27)),"! arrival misses every onward bank",IF(AND(J16=0,D16>MIN($H$5:$H$27)),"! departure has no feeder","OK")) -> OK
... A27: R23 | B27: BOM | C27: =INDEX(Markets!$F$5:$F$10,MATCH(B27,Markets!$A$5:$A$10,0)) -> A320 | D27: 0.77083333 | E27: =INDEX(Route_PnL!$D$5:$D$10,MATCH(B27,Route_PnL!$A$5:$A$10,0)) -> 1.55625 | F27: =D27+E27/24 -> 0.83567708 | G27: =F27+INDEX(Inputs!$G$14:$G$15,MATCH(C27,Inputs!$A$14:$A$15,0))/1440 -> 0.86692708 | H27: =G27+E27/24 -> 0.93177083 | I27: =SUMPRODUCT(($D$5:$D$27-H27>=Inputs!$B$7/1440)*($D$5:$D$27-H27<=Inputs!$B$8/1440)*($B$5:$B$27<>B27)) -> 0 | J27: =SUMPRODUCT((D27-$H$5:$H$27>=Inputs!$B$7/1440)*(D27-$H$5:$H$27<=Inputs!$B$8/1440)*($B$5:$B$27<>B27)) -> 5 | K27: =IF(AND(I27=0,H27<MAX($D$5:$D$27)),"! arrival misses every onward bank",IF(AND(J27=0,D27>MIN($H$5:$H$27)),"! departure has no feeder","OK")) -> OK
A29: Note: block time depends on aircraft and distance (Route_PnL). The number of rotations per spoke here drives scheduled frequency in Route_PnL. Times are one synthetic day.

Sheet Route_PnL
A1: Route economics (daily, both directions unless stated)
A2: Formulas only - change Inputs, Markets or Schedule. Capacity/demand/passengers are per direction; revenue, cost, profit, ASK, RPK are both directions.
A4: Spoke | B4: Aircraft | C4: Seats | D4: Block time (hrs) | E4: Scheduled rotations | F4: Daily flights per direction | G4: Capacity (pax/dir/day) | H4: Demand (pax/dir/day) | I4: Passengers carried (per dir) | J4: Spill (pax/dir) | K4: Load factor | L4: Fare (INR) | M4: Revenue (INR/day) | N4: Cost (INR/day) | O4: Profit (INR/day) | P4: ASK/day | Q4: RPK/day | R4: RASK (INR) | S4: CASK (INR) | T4: Yield (INR/RPK) | U4: Breakeven load factor | V4: Cushion (LF pts) | W4: Recommendation | X4: Profit change from adding 1 daily flight each way (INR/day)
A5: =Markets!A5 -> TRV | B5: =Markets!F5 -> A320 | C5: =INDEX(Inputs!$B$14:$B$15,MATCH(B5,Inputs!$A$14:$A$15,0)) -> 180 | D5: =Markets!C5/INDEX(Inputs!$C$14:$C$15,MATCH(B5,Inputs!$A$14:$A$15,0))+INDEX(Inputs!$D$14:$D$15,MATCH(B5,Inputs!$A$14:$A$15,0)) -> 1.13125 | E5: =COUNTIF(Schedule!$B$5:$B$27,A5) -> 4 | F5: =MAX(0,E5+Markets!G5) -> 4 | G5: =F5*C5 -> 720 | H5: =Markets!D5*(1+Inputs!$B$4) -> 640 | I5: =MIN(G5,H5) -> 640 | J5: =MAX(0,H5-G5) -> 0 | K5: =IF(G5=0,0,I5/G5) -> 0.88888889 | L5: =Markets!E5*(1+Inputs!$B$5) -> 4500 | M5: =I5*L5*2 -> 5760000 | N5: =F5*2*(D5*INDEX(Inputs!$E$14:$E$15,MATCH(B5,Inputs!$A$14:$A$15,0))+INDEX(Inputs!$F$14:$F$15,MATCH(B5,Inputs!$A$14:$A$15,0)))*(1+Inputs!$B$6) -> 5544000 | O5: =M5-N5 -> 216000 | P5: =G5*Markets!C5*2 -> 727200 | Q5: =I5*Markets!C5*2 -> 646400 | R5: =IF(P5=0,0,M5/P5) -> 7.9207921 | S5: =IF(P5=0,0,N5/P5) -> 7.6237624 | T5: =IF(Q5=0,0,M5/Q5) -> 8.9108911 | U5: =IF(G5*L5=0,0,N5/(L5*G5*2)) -> 0.85555556 | V5: =K5-U5 -> 0.033333333 | W5: =IF(AND(J5>Inputs!$B$9*H5,X5>0),"ADD capacity / upgauge",IF(J5>Inputs!$B$9*H5,"HOLD: spill too small to fill another flight - test pricing",IF(O5<0,"REVIEW: losing money - downgauge or cut",IF(V5<Inputs!$B$10,"WATCH: thin margin","HOLD")))) -> HOLD | X5: =(MIN((F5+1)*C5,H5)*L5*2-(F5+1)*2*(D5*INDEX(Inputs!$E$14:$E$15,MATCH(B5,Inputs!$A$14:$A$15,0))+INDEX(Inputs!$F$14:$F$15,MATCH(B5,Inputs!$A$14:$A$15,0)))*(1+Inputs!$B$6))-O5 -> -1386000
A6: =Markets!A6 -> COK | B6: =Markets!F6 -> ATR72 | C6: =INDEX(Inputs!$B$14:$B$15,MATCH(B6,Inputs!$A$14:$A$15,0)) -> 78 | D6: =Markets!C6/INDEX(Inputs!$C$14:$C$15,MATCH(B6,Inputs!$A$14:$A$15,0))+INDEX(Inputs!$D$14:$D$15,MATCH(B6,Inputs!$A$14:$A$15,0)) -> 1.08 | E6: =COUNTIF(Schedule!$B$5:$B$27,A6) -> 4 | F6: =MAX(0,E6+Markets!G6) -> 4 | G6: =F6*C6 -> 312 | H6: =Markets!D6*(1+Inputs!$B$4) -> 300 | I6: =MIN(G6,H6) -> 300 | J6: =MAX(0,H6-G6) -> 0 | K6: =IF(G6=0,0,I6/G6) -> 0.96153846 | L6: =Markets!E6*(1+Inputs!$B$5) -> 3200 | M6: =I6*L6*2 -> 1920000 | N6: =F6*2*(D6*INDEX(Inputs!$E$14:$E$15,MATCH(B6,Inputs!$A$14:$A$15,0))+INDEX(Inputs!$F$14:$F$15,MATCH(B6,Inputs!$A$14:$A$15,0)))*(1+Inputs!$B$6) -> 1696000 | O6: =M6-N6 -> 224000 | P6: =G6*Markets!C6*2 -> 212160 | Q6: =I6*Markets!C6*2 -> 204000 | R6: =IF(P6=0,0,M6/P6) -> 9.0497738 | S6: =IF(P6=0,0,N6/P6) -> 7.9939668 | T6: =IF(Q6=0,0,M6/Q6) -> 9.4117647 | U6: =IF(G6*L6=0,0,N6/(L6*G6*2)) -> 0.84935897 | V6: =K6-U6 -> 0.11217949 | W6: =IF(AND(J6>Inputs!$B$9*H6,X6>0),"ADD capacity / upgauge",IF(J6>Inputs!$B$9*H6,"HOLD: spill too small to fill another flight - test pricing",IF(O6<0,"REVIEW: losing money - downgauge or cut",IF(V6<Inputs!$B$10,"WATCH: thin margin","HOLD")))) -> HOLD | X6: =(MIN((F6+1)*C6,H6)*L6*2-(F6+1)*2*(D6*INDEX(Inputs!$E$14:$E$15,MATCH(B6,Inputs!$A$14:$A$15,0))+INDEX(Inputs!$F$14:$F$15,MATCH(B6,Inputs!$A$14:$A$15,0)))*(1+Inputs!$B$6))-O6 -> -424000
A7: =Markets!A7 -> HYD | B7: =Markets!F7 -> A320 | C7: =INDEX(Inputs!$B$14:$B$15,MATCH(B7,Inputs!$A$14:$A$15,0)) -> 180 | D7: =Markets!C7/INDEX(Inputs!$C$14:$C$15,MATCH(B7,Inputs!$A$14:$A$15,0))+INDEX(Inputs!$D$14:$D$15,MATCH(B7,Inputs!$A$14:$A$15,0)) -> 1.125 | E7: =COUNTIF(Schedule!$B$5:$B$27,A7) -> 4 | F7: =MAX(0,E7+Markets!G7) -> 4 | G7: =F7*C7 -> 720 | H7: =Markets!D7*(1+Inputs!$B$4) -> 640 | I7: =MIN(G7,H7) -> 640 | J7: =MAX(0,H7-G7) -> 0 | K7: =IF(G7=0,0,I7/G7) -> 0.88888889 | L7: =Markets!E7*(1+Inputs!$B$5) -> 4800 | M7: =I7*L7*2 -> 6144000 | N7: =F7*2*(D7*INDEX(Inputs!$E$14:$E$15,MATCH(B7,Inputs!$A$14:$A$15,0))+INDEX(Inputs!$F$14:$F$15,MATCH(B7,Inputs!$A$14:$A$15,0)))*(1+Inputs!$B$6) -> 5520000 | O7: =M7-N7 -> 624000 | P7: =G7*Markets!C7*2 -> 720000 | Q7: =I7*Markets!C7*2 -> 640000 | R7: =IF(P7=0,0,M7/P7) -> 8.5333333 | S7: =IF(P7=0,0,N7/P7) -> 7.6666667 | T7: =IF(Q7=0,0,M7/Q7) -> 9.6 | U7: =IF(G7*L7=0,0,N7/(L7*G7*2)) -> 0.79861111 | V7: =K7-U7 -> 0.090277778 | W7: =IF(AND(J7>Inputs!$B$9*H7,X7>0),"ADD capacity / upgauge",IF(J7>Inputs!$B$9*H7,"HOLD: spill too small to fill another flight - test pricing",IF(O7<0,"REVIEW: losing money - downgauge or cut",IF(V7<Inputs!$B$10,"WATCH: thin margin","HOLD")))) -> HOLD | X7: =(MIN((F7+1)*C7,H7)*L7*2-(F7+1)*2*(D7*INDEX(Inputs!$E$14:$E$15,MATCH(B7,Inputs!$A$14:$A$15,0))+INDEX(Inputs!$F$14:$F$15,MATCH(B7,Inputs!$A$14:$A$15,0)))*(1+Inputs!$B$6))-O7 -> -1380000
A8: =Markets!A8 -> MAA | B8: =Markets!F8 -> A320 | C8: =INDEX(Inputs!$B$14:$B$15,MATCH(B8,Inputs!$A$14:$A$15,0)) -> 180 | D8: =Markets!C8/INDEX(Inputs!$C$14:$C$15,MATCH(B8,Inputs!$A$14:$A$15,0))+INDEX(Inputs!$D$14:$D$15,MATCH(B8,Inputs!$A$14:$A$15,0)) -> 0.8625 | E8: =COUNTIF(Schedule!$B$5:$B$27,A8) -> 3 | F8: =MAX(0,E8+Markets!G8) -> 3 | G8: =F8*C8 -> 540 | H8: =Markets!D8*(1+Inputs!$B$4) -> 480 | I8: =MIN(G8,H8) -> 480 | J8: =MAX(0,H8-G8) -> 0 | K8: =IF(G8=0,0,I8/G8) -> 0.88888889 | L8: =Markets!E8*(1+Inputs!$B$5) -> 3200 | M8: =I8*L8*2 -> 3072000 | N8: =F8*2*(D8*INDEX(Inputs!$E$14:$E$15,MATCH(B8,Inputs!$A$14:$A$15,0))+INDEX(Inputs!$F$14:$F$15,MATCH(B8,Inputs!$A$14:$A$15,0)))*(1+Inputs!$B$6) -> 3384000 | O8: =M8-N8 -> -312000 | P8: =G8*Markets!C8*2 -> 313200 | Q8: =I8*Markets!C8*2 -> 278400 | R8: =IF(P8=0,0,M8/P8) -> 9.8084291 | S8: =IF(P8=0,0,N8/P8) -> 10.804598 | T8: =IF(Q8=0,0,M8/Q8) -> 11.034483 | U8: =IF(G8*L8=0,0,N8/(L8*G8*2)) -> 0.97916667 | V8: =K8-U8 -> -0.090277778 | W8: =IF(AND(J8>Inputs!$B$9*H8,X8>0),"ADD capacity / upgauge",IF(J8>Inputs!$B$9*H8,"HOLD: spill too small to fill another flight - test pricing",IF(O8<0,"REVIEW: losing money - downgauge or cut",IF(V8<Inputs!$B$10,"WATCH: thin margin","HOLD")))) -> REVIEW: losing money - downgauge or cut | X8: =(MIN((F8+1)*C8,H8)*L8*2-(F8+1)*2*(D8*INDEX(Inputs!$E$14:$E$15,MATCH(B8,Inputs!$A$14:$A$15,0))+INDEX(Inputs!$F$14:$F$15,MATCH(B8,Inputs!$A$14:$A$15,0)))*(1+Inputs!$B$6))-O8 -> -1128000
A9: =Markets!A9 -> GOI | B9: =Markets!F9 -> A320 | C9: =INDEX(Inputs!$B$14:$B$15,MATCH(B9,Inputs!$A$14:$A$15,0)) -> 180 | D9: =Markets!C9/INDEX(Inputs!$C$14:$C$15,MATCH(B9,Inputs!$A$14:$A$15,0))+INDEX(Inputs!$D$14:$D$15,MATCH(B9,Inputs!$A$14:$A$15,0)) -> 1.10625 | E9: =COUNTIF(Schedule!$B$5:$B$27,A9) -> 3 | F9: =MAX(0,E9+Markets!G9) -> 3 | G9: =F9*C9 -> 540 | H9: =Markets!D9*(1+Inputs!$B$4) -> 440 | I9: =MIN(G9,H9) -> 440 | J9: =MAX(0,H9-G9) -> 0 | K9: =IF(G9=0,0,I9/G9) -> 0.81481481 | L9: =Markets!E9*(1+Inputs!$B$5) -> 4500 | M9: =I9*L9*2 -> 3960000 | N9: =F9*2*(D9*INDEX(Inputs!$E$14:$E$15,MATCH(B9,Inputs!$A$14:$A$15,0))+INDEX(Inputs!$F$14:$F$15,MATCH(B9,Inputs!$A$14:$A$15,0)))*(1+Inputs!$B$6) -> 4086000 | O9: =M9-N9 -> -126000 | P9: =G9*Markets!C9*2 -> 523800 | Q9: =I9*Markets!C9*2 -> 426800 | R9: =IF(P9=0,0,M9/P9) -> 7.5601375 | S9: =IF(P9=0,0,N9/P9) -> 7.8006873 | T9: =IF(Q9=0,0,M9/Q9) -> 9.2783505 | U9: =IF(G9*L9=0,0,N9/(L9*G9*2)) -> 0.84074074 | V9: =K9-U9 -> -0.025925926 | W9: =IF(AND(J9>Inputs!$B$9*H9,X9>0),"ADD capacity / upgauge",IF(J9>Inputs!$B$9*H9,"HOLD: spill too small to fill another flight - test pricing",IF(O9<0,"REVIEW: losing money - downgauge or cut",IF(V9<Inputs!$B$10,"WATCH: thin margin","HOLD")))) -> REVIEW: losing money - downgauge or cut | X9: =(MIN((F9+1)*C9,H9)*L9*2-(F9+1)*2*(D9*INDEX(Inputs!$E$14:$E$15,MATCH(B9,Inputs!$A$14:$A$15,0))+INDEX(Inputs!$F$14:$F$15,MATCH(B9,Inputs!$A$14:$A$15,0)))*(1+Inputs!$B$6))-O9 -> -1362000
A10: =Markets!A10 -> BOM | B10: =Markets!F10 -> A320 | C10: =INDEX(Inputs!$B$14:$B$15,MATCH(B10,Inputs!$A$14:$A$15,0)) -> 180 | D10: =Markets!C10/INDEX(Inputs!$C$14:$C$15,MATCH(B10,Inputs!$A$14:$A$15,0))+INDEX(Inputs!$D$14:$D$15,MATCH(B10,Inputs!$A$14:$A$15,0)) -> 1.55625 | E10: =COUNTIF(Schedule!$B$5:$B$27,A10) -> 5 | F10: =MAX(0,E10+Markets!G10) -> 5 | G10: =F10*C10 -> 900 | H10: =Markets!D10*(1+Inputs!$B$4) -> 980 | I10: =MIN(G10,H10) -> 900 | J10: =MAX(0,H10-G10) -> 80 | K10: =IF(G10=0,0,I10/G10) -> 1 | L10: =Markets!E10*(1+Inputs!$B$5) -> 6200 | M10: =I10*L10*2 -> 11160000 | N10: =F10*2*(D10*INDEX(Inputs!$E$14:$E$15,MATCH(B10,Inputs!$A$14:$A$15,0))+INDEX(Inputs!$F$14:$F$15,MATCH(B10,Inputs!$A$14:$A$15,0)))*(1+Inputs!$B$6) -> 8970000 | O10: =M10-N10 -> 2190000 | P10: =G10*Markets!C10*2 -> 1521000 | Q10: =I10*Markets!C10*2 -> 1521000 | R10: =IF(P10=0,0,M10/P10) -> 7.3372781 | S10: =IF(P10=0,0,N10/P10) -> 5.8974359 | T10: =IF(Q10=0,0,M10/Q10) -> 7.3372781 | U10: =IF(G10*L10=0,0,N10/(L10*G10*2)) -> 0.80376344 | V10: =K10-U10 -> 0.19623656 | W10: =IF(AND(J10>Inputs!$B$9*H10,X10>0),"ADD capacity / upgauge",IF(J10>Inputs!$B$9*H10,"HOLD: spill too small to fill another flight - test pricing",IF(O10<0,"REVIEW: losing money - downgauge or cut",IF(V10<Inputs!$B$10,"WATCH: thin margin","HOLD")))) -> HOLD: spill too small to fill another flight - test pricing | X10: =(MIN((F10+1)*C10,H10)*L10*2-(F10+1)*2*(D10*INDEX(Inputs!$E$14:$E$15,MATCH(B10,Inputs!$A$14:$A$15,0))+INDEX(Inputs!$F$14:$F$15,MATCH(B10,Inputs!$A$14:$A$15,0)))*(1+Inputs!$B$6))-O10 -> -802000
A11: NETWORK | E11: =SUM(E5:E10) -> 23 | F11: =SUM(F5:F10) -> 23 | G11: =SUM(G5:G10) -> 3732 | H11: =SUM(H5:H10) -> 3480 | I11: =SUM(I5:I10) -> 3400 | J11: =SUM(J5:J10) -> 80 | K11: =IF(P11=0,0,Q11/P11) -> 0.92513491 | M11: =SUM(M5:M10) -> 32016000 | N11: =SUM(N5:N10) -> 29200000 | O11: =SUM(O5:O10) -> 2816000 | P11: =SUM(P5:P10) -> 4017360 | Q11: =SUM(Q5:Q10) -> 3716600 | R11: =IF(P11=0,0,M11/P11) -> 7.9694127 | S11: =IF(P11=0,0,N11/P11) -> 7.2684549 | T11: =IF(Q11=0,0,M11/Q11) -> 8.6143249 | U11: =IF(M11=0,0,N11*K11/M11) -> 0.84376373 | V11: =K11-U11 -> 0.081371187
A12: Network load factor = total RPK / total ASK (distance-weighted). Network breakeven LF = cost / revenue at 100% load factor.
